[
  {
    "nom": "WWR5FS9Z3",
    "poblacio": "Sant Gregori",
    "direccio": "Carrer FRANCESC DE VERNTALLAT 20",
    "energia": "20",
    "emissions": "6.95",
    "ve": true,
    "solar_fv": false,
    "solar_ter": false,
    "classificacio": "A",
    "dinersAlMes": 7000,
    "userId": 1,
    "energiaIni": "20",
    "classificacioIni": "A"
  },
  {
    "nom": "7QBPBBBMJ",
    "poblacio": "Sant Gregori",
    "direccio": "Carrer FRANCESC DE VERNTALLAT 26",
    "energia": "25",
    "emissions": "6.73",
    "ve": true,
    "solar_fv": false,
    "solar_ter": false,
    "classificacio": "A",
    "dinersAlMes": 7000,
    "userId": 2,
    "energiaIni": "25",
    "classificacioIni": "A"
  },
  {
    "nom": "W1TTK59L3",
    "poblacio": "Navata",
    "direccio": "Avinguda MAS FRIGÓL (A3-7) 47",
    "energia": "30",
    "emissions": "5.25",
    "ve": false,
    "solar_fv": false,
    "solar_ter": false,
    "classificacio": "A",
    "dinersAlMes": 7000,
    "userId": 3,
    "energiaIni": "30",
    "classificacioIni": "A"
  },
  {
    "nom": "L488TMXH1",
    "poblacio": "Santa Margarida i els Monjos",
    "direccio": "Avinguda Cal Salines 52 B",
    "energia": "35",
    "emissions": "6.69",
    "ve": false,
    "solar_fv": false,
    "solar_ter": false,
    "classificacio": "A",
    "dinersAlMes": 7000,
    "userId": 4,
    "energiaIni": "35",
    "classificacioIni": "A"
  },
  {
    "nom": "1L0XVHNXD",
    "poblacio": "Gavà",
    "direccio": "Carrer Cal Mas 9",
    "energia": "40",
    "emissions": "4.49",
    "ve": false,
    "solar_fv": false,
    "solar_ter": false,
    "classificacio": "A",
    "dinersAlMes": 7000,
    "userId": 5,
    "energiaIni": "40",
    "classificacioIni": "A"
  },
  {
    "nom": "594ML4CZ7",
    "poblacio": "Sant Boi de Lluçanès",
    "direccio": "Carrer CAMI DEL VILAR 18",
    "energia": "47",
    "emissions": "12.63",
    "ve": false,
    "solar_fv": false,
    "solar_ter": false,
    "classificacio": "B",
    "dinersAlMes": 6000,
    "userId": 6,
    "energiaIni": "47",
    "classificacioIni": "B"
  },
  {
    "nom": "86Z8L982W",
    "poblacio": "Vilafant",
    "direccio": "Carrer Mercè Rodoreda 14",
    "energia": "49",
    "emissions": "8.42",
    "ve": true,
    "solar_fv": false,
    "solar_ter": false,
    "classificacio": "B",
    "dinersAlMes": 6000,
    "userId": 7,
    "energiaIni": "49",
    "classificacioIni": "B"
  },
  {
    "nom": "NZVLD066T",
    "poblacio": "Armentera (L')",
    "direccio": "Carrer Jacint Verdaguer 3",
    "energia": "50",
    "emissions": "8.58",
    "ve": false,
    "solar_fv": false,
    "solar_ter": false,
    "classificacio": "B",
    "dinersAlMes": 6000,
    "userId": 8,
    "energiaIni": "50",
    "classificacioIni": "B"
  },
  {
    "nom": "VHGKXP3FF",
    "poblacio": "Santa Coloma de Gramenet",
    "direccio": "Carrer D'EN BARÓ 31",
    "energia": "55",
    "emissions": "7.66",
    "ve": false,
    "solar_fv": false,
    "solar_ter": false,
    "classificacio": "B",
    "dinersAlMes": 6000,
    "userId": 9,
    "energiaIni": "55",
    "classificacioIni": "B"
  },
  {
    "nom": "YV234C4L4",
    "poblacio": "Prat de Llobregat (El)",
    "direccio": "Carrer JAUME CASANOVAS 270",
    "energia": "60",
    "emissions": "7.62",
    "ve": false,
    "solar_fv": false,
    "solar_ter": false,
    "classificacio": "B",
    "dinersAlMes": 6000,
    "userId": 10,
    "energiaIni": "60",
    "classificacioIni": "B"
  },
  {
    "nom": "HTGQTMZD7",
    "poblacio": "Albons",
    "direccio": "Carrer OLIVERA 3",
    "energia": "75",
    "emissions": "12.27",
    "ve": false,
    "solar_fv": false,
    "solar_ter": false,
    "classificacio": "C",
    "dinersAlMes": 5000,
    "userId": 11,
    "energiaIni": "75",
    "classificacioIni": "C"
  },
  {
    "nom": "96JFP9P79",
    "poblacio": "Escala (L')",
    "direccio": "Carrer Trencabraços 29",
    "energia": "80",
    "emissions": "15.25",
    "ve": false,
    "solar_fv": false,
    "solar_ter": false,
    "classificacio": "C",
    "dinersAlMes": 5000,
    "userId": 12,
    "energiaIni": "80",
    "classificacioIni": "C"
  },
  {
    "nom": "96JFP9P79",
    "poblacio": "Escala (L')",
    "direccio": "Carrer Trencabraços 29",
    "energia": "85",
    "emissions": "15.25",
    "ve": false,
    "solar_fv": false,
    "solar_ter": false,
    "classificacio": "C",
    "dinersAlMes": 5000,
    "userId": 13,
    "energiaIni": "85",
    "classificacioIni": "C"
  },
  {
    "nom": "Y0FFNDK7L",
    "poblacio": "Seu d'Urgell (La)",
    "direccio": "Polígon PARCEL·LA 89 3",
    "energia": "90",
    "emissions": "26.55",
    "ve": false,
    "solar_fv": false,
    "solar_ter": false,
    "classificacio": "C",
    "dinersAlMes": 5000,
    "userId": 14,
    "energiaIni": "90",
    "classificacioIni": "C"
  },
  {
    "nom": "VS8NGNGWY",
    "poblacio": "Collbató",
    "direccio": "Carrer Berga 16",
    "energia": "95",
    "emissions": "17.46",
    "ve": false,
    "solar_fv": false,
    "solar_ter": false,
    "classificacio": "C",
    "dinersAlMes": 5000,
    "userId": 15,
    "energiaIni": "95",
    "classificacioIni": "C"
  },
  {
    "nom": "72D54HZL",
    "poblacio": "Vilafant",
    "direccio": "Avenida DE LES MELIES 2 G",
    "energia": "130",
    "emissions": "27.3",
    "ve": false,
    "solar_fv": false,
    "solar_ter": false,
    "classificacio": "D",
    "dinersAlMes": 4000,
    "userId": 16,
    "energiaIni": "130",
    "classificacioIni": "D"
  },
  {
    "nom": "CM0CS5X9G",
    "poblacio": "Vilafant",
    "direccio": "Carrer RIPOLLES 116",
    "energia": "135",
    "emissions": "26.99",
    "ve": false,
    "solar_fv": false,
    "solar_ter": false,
    "classificacio": "D",
    "dinersAlMes": 4000,
    "userId": 17,
    "energiaIni": "135",
    "classificacioIni": "D"
  },
  {
    "nom": "8ZWP8TKV7",
    "poblacio": "Vilobí d'Onyar",
    "direccio": "Carretera de Girona a Santa Coloma, Km. 13",
    "energia": "140",
    "emissions": "34.44",
    "ve": false,
    "solar_fv": false,
    "solar_ter": false,
    "classificacio": "D",
    "dinersAlMes": 4000,
    "userId": 18,
    "energiaIni": "140",
    "classificacioIni": "D"
  },
  {
    "nom": "R8Z6JB1CD",
    "poblacio": "Vilallonga de Ter",
    "direccio": "Carrer SETCASES 13",
    "energia": "145",
    "emissions": "43.54",
    "ve": false,
    "solar_fv": false,
    "solar_ter": false,
    "classificacio": "D",
    "dinersAlMes": 4000,
    "userId": 19,
    "energiaIni": "145",
    "classificacioIni": "D"
  },
  {
    "nom": "5W7MHWXRW",
    "poblacio": "Vilamacolum",
    "direccio": "Carrer SANTA MARIA 4",
    "energia": "150",
    "emissions": "37.83",
    "ve": false,
    "solar_fv": false,
    "solar_ter": false,
    "classificacio": "D",
    "dinersAlMes": 4000,
    "userId": 20,
    "energiaIni": "150",
    "classificacioIni": "D"
  },
  {
    "nom": "VK0M6RG6L",
    "poblacio": "Sant Quintí de Mediona",
    "direccio": "Carrer Joan Sardà 30",
    "energia": "225",
    "emissions": "57.17",
    "ve": false,
    "solar_fv": false,
    "solar_ter": false,
    "classificacio": "E",
    "dinersAlMes": 3000,
    "userId": 21,
    "energiaIni": "225",
    "classificacioIni": "E"
  },
  {
    "nom": "7SFSWXG5L",
    "poblacio": "Sant Julià del Llor i Bonmatí",
    "direccio": "Carrer Pere Serrat 5",
    "energia": "230",
    "emissions": "62.33",
    "ve": false,
    "solar_fv": false,
    "solar_ter": false,
    "classificacio": "E",
    "dinersAlMes": 3000,
    "userId": 22,
    "energiaIni": "230",
    "classificacioIni": "E"
  },
  {
    "nom": "XZC1VZ82D",
    "poblacio": "Vila-seca",
    "direccio": "Carrer L'HEURA 2",
    "energia": "235",
    "emissions": "22.88",
    "ve": false,
    "solar_fv": false,
    "solar_ter": false,
    "classificacio": "E",
    "dinersAlMes": 3000,
    "userId": 23,
    "energiaIni": "235",
    "classificacioIni": "E"
  },
  {
    "nom": "BZNB8X8H5",
    "poblacio": "Vilobí d'Onyar",
    "direccio": "Carrer SANT ESTEVE 1",
    "energia": "240",
    "emissions": "46.1",
    "ve": false,
    "solar_fv": false,
    "solar_ter": false,
    "classificacio": "E",
    "dinersAlMes": 3000,
    "userId": 24,
    "energiaIni": "240",
    "classificacioIni": "E"
  },
  {
    "nom": "LVZ9FJ3XM",
    "poblacio": "Viladecavalls",
    "direccio": "Carrer LLEVANT 16",
    "energia": "245",
    "emissions": "28.42",
    "ve": false,
    "solar_fv": false,
    "solar_ter": false,
    "classificacio": "E",
    "dinersAlMes": 3000,
    "userId": 25,
    "energiaIni": "245",
    "classificacioIni": "E"
  },
  {
    "nom": "96RRXYH9L",
    "poblacio": "Vilafant",
    "direccio": "Carrer Canigo 5",
    "energia": "270",
    "emissions": "57.66",
    "ve": false,
    "solar_fv": false,
    "solar_ter": false,
    "classificacio": "F",
    "dinersAlMes": 2000,
    "userId": 26,
    "energiaIni": "270",
    "classificacioIni": "F"
  },
  {
    "nom": "F267BFWFY",
    "poblacio": "Massanes",
    "direccio": "Barri Cambrerol, Taller 1",
    "energia": "280",
    "emissions": "102.7",
    "ve": false,
    "solar_fv": false,
    "solar_ter": false,
    "classificacio": "F",
    "dinersAlMes": 2000,
    "userId": 27,
    "energiaIni": "280",
    "classificacioIni": "F"
  },
  {
    "nom": "2FJ33NPQ7",
    "poblacio": "Gavà",
    "direccio": "Carrer MARINADA 52",
    "energia": "290",
    "emissions": "63.21",
    "ve": false,
    "solar_fv": false,
    "solar_ter": false,
    "classificacio": "F",
    "dinersAlMes": 2000,
    "userId": 28,
    "energiaIni": "290",
    "classificacioIni": "F"
  },
  {
    "nom": "MLCHXQCKK",
    "poblacio": "Espinelves",
    "direccio": "Disseminat Molí del Clasqueró S/N",
    "energia": "300",
    "emissions": "52.83",
    "ve": false,
    "solar_fv": false,
    "solar_ter": false,
    "classificacio": "F",
    "dinersAlMes": 2000,
    "userId": 29,
    "energiaIni": "300",
    "classificacioIni": "F"
  },
  {
    "nom": "2M2PP591L",
    "poblacio": "Montblanc",
    "direccio": "Partida PD. EL CANAR POLÍGON 20 PARCEL·LA 11 S/N",
    "energia": "310",
    "emissions": "69.55",
    "ve": false,
    "solar_fv": false,
    "solar_ter": false,
    "classificacio": "F",
    "dinersAlMes": 2000,
    "userId": 30,
    "energiaIni": "310",
    "classificacioIni": "F"
  },
  {
    "nom": "HZX1PXW72",
    "poblacio": "Vilamalla",
    "direccio": "Carrer PIRINEUS 2",
    "energia": "330",
    "emissions": "53.53",
    "ve": false,
    "solar_fv": false,
    "solar_ter": false,
    "classificacio": "G",
    "dinersAlMes": 1000,
    "userId": 31,
    "energiaIni": "330",
    "classificacioIni": "G"
  },
  {
    "nom": "RFD7K19G3",
    "poblacio": "Lleida",
    "direccio": "Partida GREALO 152",
    "energia": "340",
    "emissions": "107.61",
    "ve": false,
    "solar_fv": false,
    "solar_ter": false,
    "classificacio": "G",
    "dinersAlMes": 1000,
    "userId": 32,
    "energiaIni": "340",
    "classificacioIni": "G"
  },
  {
    "nom": "S4KQQ8DJ1",
    "poblacio": "Sabadell",
    "direccio": "Plaça DELS MERINALS 95",
    "energia": "350",
    "emissions": "57.16",
    "ve": false,
    "solar_fv": false,
    "solar_ter": false,
    "classificacio": "G",
    "dinersAlMes": 1000,
    "userId": 33,
    "energiaIni": "350",
    "classificacioIni": "G"
  },
  {
    "nom": "GJH13V6K5",
    "poblacio": "Vilallonga de Ter",
    "direccio": "Carrer SANT DOMINGO 18",
    "energia": "360",
    "emissions": "86.87",
    "ve": false,
    "solar_fv": false,
    "solar_ter": false,
    "classificacio": "G",
    "dinersAlMes": 1000,
    "userId": 34,
    "energiaIni": "360",
    "classificacioIni": "G"
  },
  {
    "nom": "LT1K5JJ8F",
    "poblacio": "Sils",
    "direccio": "Carrer Camí Reial 4",
    "energia": "370",
    "emissions": "118.11",
    "ve": false,
    "solar_fv": false,
    "solar_ter": false,
    "classificacio": "G",
    "dinersAlMes": 1000,
    "userId": 35,
    "energiaIni": "370",
    "classificacioIni": "G"
  }
]
